git_check_ignore/__init__.py
git_check_ignore/py.typed
git_check_ignore-1.0.1.dist-info/METADATA
git_check_ignore-1.0.1.dist-info/WHEEL
git_check_ignore-1.0.1.dist-info/licenses/COPYING
git_check_ignore-1.0.1.dist-info/RECORD
