Metadata-Version: 2.4
Name: git-check-ignore
Version: 1.0.1
Summary: A Python wrapper around `git` to check filenames against `.gitignore` files
Project-URL: Documentation, https://dd-dockyard.github.io/git-check-ignore/
Project-URL: Repository, https://github.com/dd-dockyard/git-check-ignore
Project-URL: Issues, https://github.com/dd-dockyard/git-check-ignore/issues
Author-email: Jordan Webb <jordan@dangerdevices.com>
License-Expression: AGPL-3.0-only
License-File: COPYING
Keywords: git,gitignore
Classifier: Development Status :: 4 - Beta
Classifier: Intended Audience :: Developers
Classifier: License :: OSI Approved :: GNU Affero General Public License v3
Classifier: Programming Language :: Python :: 3
Classifier: Programming Language :: Python :: 3.11
Classifier: Programming Language :: Python :: 3.12
Classifier: Programming Language :: Python :: 3.13
Classifier: Topic :: Software Development :: Version Control :: Git
Requires-Python: >=3.11
